{
  "swagger": "2.0",
  "info": {
    "title": "Ventas KINAL",
    "description": "Un API para ventas de productos",
    "version": "1.0.0"
  },
  "host": "localhost:3200",
  "basePath": "/",
  "tags": [],
  "schemes": [
    "http"
  ],
  "consumes": [],
  "produces": [],
  "paths": {
    "/": {
      "get": {
        "tags": [],
        "description": "",
        "parameters": [],
        "responses": {
          "200": {
            "description": "OK"
          },
          "401": {
            "description": "Unauthorized"
          },
          "403": {
            "description": "Forbidden"
          },
          "404": {
            "description": "Not Found"
          },
          "500": {
            "description": "Internal Server Error"
          }
        }
      }
    },
    "/buy": {
      "post": {
        "tags": [],
        "description": "",
        "parameters": [],
        "responses": {
          "200": {
            "description": "OK"
          },
          "401": {
            "description": "Unauthorized"
          },
          "403": {
            "description": "Forbidden"
          },
          "404": {
            "description": "Not Found"
          },
          "500": {
            "description": "Internal Server Error"
          }
        }
      }
    },
    "/{productId}": {
      "post": {
        "tags": [],
        "description": "",
        "parameters": [
          {
            "name": "productId",
            "in": "path",
            "required": true,
            "type": "string"
          }
        ],
        "responses": {
          "200": {
            "description": "OK"
          },
          "400": {
            "description": "Bad Request"
          },
          "401": {
            "description": "Unauthorized"
          },
          "403": {
            "description": "Forbidden"
          },
          "404": {
            "description": "Not Found"
          },
          "500": {
            "description": "Internal Server Error"
          }
        }
      }
    },
    "/{userId}/saveCategory": {
      "post": {
        "tags": [],
        "description": "",
        "parameters": [
          {
            "name": "userId",
            "in": "path",
            "required": true,
            "type": "string"
          }
        ],
        "responses": {
          "401": {
            "description": "Unauthorized"
          },
          "403": {
            "description": "Forbidden"
          },
          "404": {
            "description": "Not Found"
          },
          "500": {
            "description": "Internal Server Error"
          }
        }
      }
    },
    "/{userId}/deleteCategory/{categoryId}": {
      "put": {
        "tags": [],
        "description": "",
        "parameters": [
          {
            "name": "userId",
            "in": "path",
            "required": true,
            "type": "string"
          },
          {
            "name": "categoryId",
            "in": "path",
            "required": true,
            "type": "string"
          }
        ],
        "responses": {
          "401": {
            "description": "Unauthorized"
          },
          "403": {
            "description": "Forbidden"
          },
          "404": {
            "description": "Not Found"
          },
          "500": {
            "description": "Internal Server Error"
          }
        }
      }
    },
    "/{userId}/updateCategory/{categoryId}": {
      "put": {
        "tags": [],
        "description": "",
        "parameters": [
          {
            "name": "userId",
            "in": "path",
            "required": true,
            "type": "string"
          },
          {
            "name": "categoryId",
            "in": "path",
            "required": true,
            "type": "string"
          }
        ],
        "responses": {
          "401": {
            "description": "Unauthorized"
          },
          "403": {
            "description": "Forbidden"
          },
          "404": {
            "description": "Not Found"
          },
          "500": {
            "description": "Internal Server Error"
          }
        }
      }
    },
    "/getCategory": {
      "get": {
        "tags": [],
        "description": "",
        "parameters": [],
        "responses": {
          "401": {
            "description": "Unauthorized"
          },
          "500": {
            "description": "Internal Server Error"
          }
        }
      }
    },
    "/{userId}/getCategoryId/{categoryId}": {
      "get": {
        "tags": [],
        "description": "",
        "parameters": [
          {
            "name": "userId",
            "in": "path",
            "required": true,
            "type": "string"
          },
          {
            "name": "categoryId",
            "in": "path",
            "required": true,
            "type": "string"
          }
        ],
        "responses": {
          "401": {
            "description": "Unauthorized"
          },
          "403": {
            "description": "Forbidden"
          },
          "404": {
            "description": "Not Found"
          },
          "500": {
            "description": "Internal Server Error"
          }
        }
      }
    },
    "/createProduct/{idC}": {
      "post": {
        "tags": [],
        "description": "",
        "parameters": [
          {
            "name": "idC",
            "in": "path",
            "required": true,
            "type": "string"
          }
        ],
        "responses": {
          "400": {
            "description": "Bad Request"
          },
          "401": {
            "description": "Unauthorized"
          },
          "403": {
            "description": "Forbidden"
          },
          "404": {
            "description": "Not Found"
          },
          "500": {
            "description": "Internal Server Error"
          }
        }
      }
    },
    "/getProduct/{idP}": {
      "get": {
        "tags": [],
        "description": "",
        "parameters": [
          {
            "name": "idP",
            "in": "path",
            "required": true,
            "type": "string"
          }
        ],
        "responses": {
          "400": {
            "description": "Bad Request"
          },
          "401": {
            "description": "Unauthorized"
          },
          "403": {
            "description": "Forbidden"
          },
          "404": {
            "description": "Not Found"
          },
          "500": {
            "description": "Internal Server Error"
          }
        }
      }
    },
    "/getProducts/": {
      "get": {
        "tags": [],
        "description": "",
        "parameters": [],
        "responses": {
          "404": {
            "description": "Not Found"
          },
          "500": {
            "description": "Internal Server Error"
          }
        }
      }
    },
    "/{idC}/updateProduct/{idP}": {
      "put": {
        "tags": [],
        "description": "",
        "parameters": [
          {
            "name": "idC",
            "in": "path",
            "required": true,
            "type": "string"
          },
          {
            "name": "idP",
            "in": "path",
            "required": true,
            "type": "string"
          }
        ],
        "responses": {
          "400": {
            "description": "Bad Request"
          },
          "401": {
            "description": "Unauthorized"
          },
          "403": {
            "description": "Forbidden"
          },
          "404": {
            "description": "Not Found"
          },
          "500": {
            "description": "Internal Server Error"
          }
        }
      }
    },
    "/{idC}/updateStockProduct/{idP}": {
      "put": {
        "tags": [],
        "description": "",
        "parameters": [
          {
            "name": "idC",
            "in": "path",
            "required": true,
            "type": "string"
          },
          {
            "name": "idP",
            "in": "path",
            "required": true,
            "type": "string"
          }
        ],
        "responses": {
          "400": {
            "description": "Bad Request"
          },
          "401": {
            "description": "Unauthorized"
          },
          "403": {
            "description": "Forbidden"
          },
          "404": {
            "description": "Not Found"
          },
          "500": {
            "description": "Internal Server Error"
          }
        }
      }
    },
    "/{idC}/removeProduct/{idP}": {
      "put": {
        "tags": [],
        "description": "",
        "parameters": [
          {
            "name": "idC",
            "in": "path",
            "required": true,
            "type": "string"
          },
          {
            "name": "idP",
            "in": "path",
            "required": true,
            "type": "string"
          }
        ],
        "responses": {
          "400": {
            "description": "Bad Request"
          },
          "401": {
            "description": "Unauthorized"
          },
          "403": {
            "description": "Forbidden"
          },
          "404": {
            "description": "Not Found"
          },
          "500": {
            "description": "Internal Server Error"
          }
        }
      }
    },
    "/saveUser": {
      "post": {
        "tags": [],
        "description": "",
        "parameters": [],
        "responses": {
          "401": {
            "description": "Unauthorized"
          },
          "500": {
            "description": "Internal Server Error"
          }
        }
      }
    },
    "/saveUserByAdmin/{userId}": {
      "post": {
        "tags": [],
        "description": "",
        "parameters": [
          {
            "name": "userId",
            "in": "path",
            "required": true,
            "type": "string"
          }
        ],
        "responses": {
          "401": {
            "description": "Unauthorized"
          },
          "403": {
            "description": "Forbidden"
          },
          "404": {
            "description": "Not Found"
          },
          "500": {
            "description": "Internal Server Error"
          }
        }
      }
    },
    "/login": {
      "post": {
        "tags": [],
        "description": "",
        "parameters": [],
        "responses": {
          "401": {
            "description": "Unauthorized"
          },
          "403": {
            "description": "Forbidden"
          },
          "500": {
            "description": "Internal Server Error"
          }
        }
      }
    },
    "/getUser": {
      "get": {
        "tags": [],
        "description": "",
        "parameters": [],
        "responses": {
          "401": {
            "description": "Unauthorized"
          },
          "403": {
            "description": "Forbidden"
          },
          "404": {
            "description": "Not Found"
          },
          "500": {
            "description": "Internal Server Error"
          }
        }
      }
    },
    "/getImage/{fileName}": {
      "get": {
        "tags": [],
        "description": "",
        "parameters": [
          {
            "name": "fileName",
            "in": "path",
            "required": true,
            "type": "string"
          }
        ],
        "responses": {
          "404": {
            "description": "Not Found"
          }
        }
      }
    },
    "/updateUser/{userId}": {
      "put": {
        "tags": [],
        "description": "",
        "parameters": [
          {
            "name": "userId",
            "in": "path",
            "required": true,
            "type": "string"
          }
        ],
        "responses": {
          "401": {
            "description": "Unauthorized"
          },
          "403": {
            "description": "Forbidden"
          },
          "404": {
            "description": "Not Found"
          },
          "500": {
            "description": "Internal Server Error"
          }
        }
      }
    },
    "/removeUser/{userId}": {
      "put": {
        "tags": [],
        "description": "",
        "parameters": [
          {
            "name": "userId",
            "in": "path",
            "required": true,
            "type": "string"
          }
        ],
        "responses": {
          "401": {
            "description": "Unauthorized"
          },
          "403": {
            "description": "Forbidden"
          },
          "404": {
            "description": "Not Found"
          },
          "500": {
            "description": "Internal Server Error"
          }
        }
      }
    },
    "/{userId}/deleteUserAdmin/{userId2}": {
      "put": {
        "tags": [],
        "description": "",
        "parameters": [
          {
            "name": "userId",
            "in": "path",
            "required": true,
            "type": "string"
          },
          {
            "name": "userId2",
            "in": "path",
            "required": true,
            "type": "string"
          }
        ],
        "responses": {
          "401": {
            "description": "Unauthorized"
          },
          "403": {
            "description": "Forbidden"
          },
          "404": {
            "description": "Not Found"
          },
          "500": {
            "description": "Internal Server Error"
          }
        }
      }
    },
    "/{userId}/UpdateUserAdmin/{userId2}": {
      "put": {
        "tags": [],
        "description": "",
        "parameters": [
          {
            "name": "userId",
            "in": "path",
            "required": true,
            "type": "string"
          },
          {
            "name": "userId2",
            "in": "path",
            "required": true,
            "type": "string"
          }
        ],
        "responses": {
          "401": {
            "description": "Unauthorized"
          },
          "403": {
            "description": "Forbidden"
          },
          "404": {
            "description": "Not Found"
          },
          "500": {
            "description": "Internal Server Error"
          }
        }
      }
    },
    "/{userId}/uploadImageUser": {
      "put": {
        "tags": [],
        "description": "",
        "parameters": [
          {
            "name": "userId",
            "in": "path",
            "required": true,
            "type": "string"
          }
        ],
        "responses": {
          "400": {
            "description": "Bad Request"
          },
          "401": {
            "description": "Unauthorized"
          },
          "403": {
            "description": "Forbidden"
          },
          "404": {
            "description": "Not Found"
          },
          "500": {
            "description": "Internal Server Error"
          }
        }
      }
    },
    "/api/saveUser": {
      "post": {
        "tags": [],
        "description": "",
        "parameters": [],
        "responses": {
          "401": {
            "description": "Unauthorized"
          },
          "500": {
            "description": "Internal Server Error"
          }
        }
      }
    },
    "/api/saveUserByAdmin/{userId}": {
      "post": {
        "tags": [],
        "description": "",
        "parameters": [
          {
            "name": "userId",
            "in": "path",
            "required": true,
            "type": "string"
          }
        ],
        "responses": {
          "401": {
            "description": "Unauthorized"
          },
          "403": {
            "description": "Forbidden"
          },
          "404": {
            "description": "Not Found"
          },
          "500": {
            "description": "Internal Server Error"
          }
        }
      }
    },
    "/api/login": {
      "post": {
        "tags": [],
        "description": "",
        "parameters": [],
        "responses": {
          "401": {
            "description": "Unauthorized"
          },
          "403": {
            "description": "Forbidden"
          },
          "500": {
            "description": "Internal Server Error"
          }
        }
      }
    },
    "/api/getUser": {
      "get": {
        "tags": [],
        "description": "",
        "parameters": [],
        "responses": {
          "401": {
            "description": "Unauthorized"
          },
          "403": {
            "description": "Forbidden"
          },
          "404": {
            "description": "Not Found"
          },
          "500": {
            "description": "Internal Server Error"
          }
        }
      }
    },
    "/api/getImage/{fileName}": {
      "get": {
        "tags": [],
        "description": "",
        "parameters": [
          {
            "name": "fileName",
            "in": "path",
            "required": true,
            "type": "string"
          }
        ],
        "responses": {
          "404": {
            "description": "Not Found"
          }
        }
      }
    },
    "/api/updateUser/{userId}": {
      "put": {
        "tags": [],
        "description": "",
        "parameters": [
          {
            "name": "userId",
            "in": "path",
            "required": true,
            "type": "string"
          }
        ],
        "responses": {
          "401": {
            "description": "Unauthorized"
          },
          "403": {
            "description": "Forbidden"
          },
          "404": {
            "description": "Not Found"
          },
          "500": {
            "description": "Internal Server Error"
          }
        }
      }
    },
    "/api/removeUser/{userId}": {
      "put": {
        "tags": [],
        "description": "",
        "parameters": [
          {
            "name": "userId",
            "in": "path",
            "required": true,
            "type": "string"
          }
        ],
        "responses": {
          "401": {
            "description": "Unauthorized"
          },
          "403": {
            "description": "Forbidden"
          },
          "404": {
            "description": "Not Found"
          },
          "500": {
            "description": "Internal Server Error"
          }
        }
      }
    },
    "/api/{userId}/deleteUserAdmin/{userId2}": {
      "put": {
        "tags": [],
        "description": "",
        "parameters": [
          {
            "name": "userId",
            "in": "path",
            "required": true,
            "type": "string"
          },
          {
            "name": "userId2",
            "in": "path",
            "required": true,
            "type": "string"
          }
        ],
        "responses": {
          "401": {
            "description": "Unauthorized"
          },
          "403": {
            "description": "Forbidden"
          },
          "404": {
            "description": "Not Found"
          },
          "500": {
            "description": "Internal Server Error"
          }
        }
      }
    },
    "/api/{userId}/UpdateUserAdmin/{userId2}": {
      "put": {
        "tags": [],
        "description": "",
        "parameters": [
          {
            "name": "userId",
            "in": "path",
            "required": true,
            "type": "string"
          },
          {
            "name": "userId2",
            "in": "path",
            "required": true,
            "type": "string"
          }
        ],
        "responses": {
          "401": {
            "description": "Unauthorized"
          },
          "403": {
            "description": "Forbidden"
          },
          "404": {
            "description": "Not Found"
          },
          "500": {
            "description": "Internal Server Error"
          }
        }
      }
    },
    "/api/{userId}/uploadImageUser": {
      "put": {
        "tags": [],
        "description": "",
        "parameters": [
          {
            "name": "userId",
            "in": "path",
            "required": true,
            "type": "string"
          }
        ],
        "responses": {
          "400": {
            "description": "Bad Request"
          },
          "401": {
            "description": "Unauthorized"
          },
          "403": {
            "description": "Forbidden"
          },
          "404": {
            "description": "Not Found"
          },
          "500": {
            "description": "Internal Server Error"
          }
        }
      }
    },
    "/api/{userId}/saveCategory": {
      "post": {
        "tags": [],
        "description": "",
        "parameters": [
          {
            "name": "userId",
            "in": "path",
            "required": true,
            "type": "string"
          }
        ],
        "responses": {
          "401": {
            "description": "Unauthorized"
          },
          "403": {
            "description": "Forbidden"
          },
          "404": {
            "description": "Not Found"
          },
          "500": {
            "description": "Internal Server Error"
          }
        }
      }
    },
    "/api/{userId}/deleteCategory/{categoryId}": {
      "put": {
        "tags": [],
        "description": "",
        "parameters": [
          {
            "name": "userId",
            "in": "path",
            "required": true,
            "type": "string"
          },
          {
            "name": "categoryId",
            "in": "path",
            "required": true,
            "type": "string"
          }
        ],
        "responses": {
          "401": {
            "description": "Unauthorized"
          },
          "403": {
            "description": "Forbidden"
          },
          "404": {
            "description": "Not Found"
          },
          "500": {
            "description": "Internal Server Error"
          }
        }
      }
    },
    "/api/{userId}/updateCategory/{categoryId}": {
      "put": {
        "tags": [],
        "description": "",
        "parameters": [
          {
            "name": "userId",
            "in": "path",
            "required": true,
            "type": "string"
          },
          {
            "name": "categoryId",
            "in": "path",
            "required": true,
            "type": "string"
          }
        ],
        "responses": {
          "401": {
            "description": "Unauthorized"
          },
          "403": {
            "description": "Forbidden"
          },
          "404": {
            "description": "Not Found"
          },
          "500": {
            "description": "Internal Server Error"
          }
        }
      }
    },
    "/api/getCategory": {
      "get": {
        "tags": [],
        "description": "",
        "parameters": [],
        "responses": {
          "401": {
            "description": "Unauthorized"
          },
          "500": {
            "description": "Internal Server Error"
          }
        }
      }
    },
    "/api/{userId}/getCategoryId/{categoryId}": {
      "get": {
        "tags": [],
        "description": "",
        "parameters": [
          {
            "name": "userId",
            "in": "path",
            "required": true,
            "type": "string"
          },
          {
            "name": "categoryId",
            "in": "path",
            "required": true,
            "type": "string"
          }
        ],
        "responses": {
          "401": {
            "description": "Unauthorized"
          },
          "403": {
            "description": "Forbidden"
          },
          "404": {
            "description": "Not Found"
          },
          "500": {
            "description": "Internal Server Error"
          }
        }
      }
    },
    "/api/createProduct/{idC}": {
      "post": {
        "tags": [],
        "description": "",
        "parameters": [
          {
            "name": "idC",
            "in": "path",
            "required": true,
            "type": "string"
          }
        ],
        "responses": {
          "400": {
            "description": "Bad Request"
          },
          "401": {
            "description": "Unauthorized"
          },
          "403": {
            "description": "Forbidden"
          },
          "404": {
            "description": "Not Found"
          },
          "500": {
            "description": "Internal Server Error"
          }
        }
      }
    },
    "/api/getProduct/{idP}": {
      "get": {
        "tags": [],
        "description": "",
        "parameters": [
          {
            "name": "idP",
            "in": "path",
            "required": true,
            "type": "string"
          }
        ],
        "responses": {
          "400": {
            "description": "Bad Request"
          },
          "401": {
            "description": "Unauthorized"
          },
          "403": {
            "description": "Forbidden"
          },
          "404": {
            "description": "Not Found"
          },
          "500": {
            "description": "Internal Server Error"
          }
        }
      }
    },
    "/api/getProducts/": {
      "get": {
        "tags": [],
        "description": "",
        "parameters": [],
        "responses": {
          "404": {
            "description": "Not Found"
          },
          "500": {
            "description": "Internal Server Error"
          }
        }
      }
    },
    "/api/{idC}/updateProduct/{idP}": {
      "put": {
        "tags": [],
        "description": "",
        "parameters": [
          {
            "name": "idC",
            "in": "path",
            "required": true,
            "type": "string"
          },
          {
            "name": "idP",
            "in": "path",
            "required": true,
            "type": "string"
          }
        ],
        "responses": {
          "400": {
            "description": "Bad Request"
          },
          "401": {
            "description": "Unauthorized"
          },
          "403": {
            "description": "Forbidden"
          },
          "404": {
            "description": "Not Found"
          },
          "500": {
            "description": "Internal Server Error"
          }
        }
      }
    },
    "/api/{idC}/updateStockProduct/{idP}": {
      "put": {
        "tags": [],
        "description": "",
        "parameters": [
          {
            "name": "idC",
            "in": "path",
            "required": true,
            "type": "string"
          },
          {
            "name": "idP",
            "in": "path",
            "required": true,
            "type": "string"
          }
        ],
        "responses": {
          "400": {
            "description": "Bad Request"
          },
          "401": {
            "description": "Unauthorized"
          },
          "403": {
            "description": "Forbidden"
          },
          "404": {
            "description": "Not Found"
          },
          "500": {
            "description": "Internal Server Error"
          }
        }
      }
    },
    "/api/{idC}/removeProduct/{idP}": {
      "put": {
        "tags": [],
        "description": "",
        "parameters": [
          {
            "name": "idC",
            "in": "path",
            "required": true,
            "type": "string"
          },
          {
            "name": "idP",
            "in": "path",
            "required": true,
            "type": "string"
          }
        ],
        "responses": {
          "400": {
            "description": "Bad Request"
          },
          "401": {
            "description": "Unauthorized"
          },
          "403": {
            "description": "Forbidden"
          },
          "404": {
            "description": "Not Found"
          },
          "500": {
            "description": "Internal Server Error"
          }
        }
      }
    },
    "/api/cart/": {
      "get": {
        "tags": [],
        "description": "",
        "parameters": [],
        "responses": {
          "200": {
            "description": "OK"
          },
          "401": {
            "description": "Unauthorized"
          },
          "403": {
            "description": "Forbidden"
          },
          "404": {
            "description": "Not Found"
          },
          "500": {
            "description": "Internal Server Error"
          }
        }
      }
    },
    "/api/cart/buy": {
      "post": {
        "tags": [],
        "description": "",
        "parameters": [],
        "responses": {
          "200": {
            "description": "OK"
          },
          "401": {
            "description": "Unauthorized"
          },
          "403": {
            "description": "Forbidden"
          },
          "404": {
            "description": "Not Found"
          },
          "500": {
            "description": "Internal Server Error"
          }
        }
      }
    },
    "/api/cart/{productId}": {
      "post": {
        "tags": [],
        "description": "",
        "parameters": [
          {
            "name": "productId",
            "in": "path",
            "required": true,
            "type": "string"
          }
        ],
        "responses": {
          "200": {
            "description": "OK"
          },
          "400": {
            "description": "Bad Request"
          },
          "401": {
            "description": "Unauthorized"
          },
          "403": {
            "description": "Forbidden"
          },
          "404": {
            "description": "Not Found"
          },
          "500": {
            "description": "Internal Server Error"
          }
        }
      }
    },
    "/api/invoice/": {
      "get": {
        "tags": [],
        "description": "",
        "parameters": [],
        "responses": {
          "200": {
            "description": "OK"
          },
          "401": {
            "description": "Unauthorized"
          },
          "403": {
            "description": "Forbidden"
          },
          "404": {
            "description": "Not Found"
          },
          "500": {
            "description": "Internal Server Error"
          }
        }
      }
    }
  },
  "definitions": {},
  "scheme": [
    "http"
  ]
}